garnett/__init__.py
garnett/ciffilereader.py
garnett/ciffilewriter.py
garnett/dcdfilereader.py
garnett/errors.py
garnett/getarfilereader.py
garnett/getarfilewriter.py
garnett/gsdhoomd.py
garnett/gsdhoomdfilereader.py
garnett/gsdhoomdfilewriter.py
garnett/hoomdxmlfilereader.py
garnett/posfilereader.py
garnett/posfilewriter.py
garnett/pydcdreader.py
garnett/pygsd.py
garnett/reader.py
garnett/samples.py
garnett/shapes.py
garnett/trajectory.py
garnett/util.py
garnett/version.py
garnett/writer.py
garnett-0.7.1.dist-info/LICENSE.txt
garnett-0.7.1.dist-info/METADATA
garnett-0.7.1.dist-info/WHEEL
garnett-0.7.1.dist-info/top_level.txt
garnett-0.7.1.dist-info/RECORD
