Metadata-Version: 2.1
Name: garnett
Version: 0.7.1
Summary: Samples, parsers, and writers for formats used in the Glotzer Group.
Home-page: https://garnett.readthedocs.io/
Author: Carl Simon Adorf et al.
Author-email: csadorf@umich.edu
Maintainer: garnett Developers
License: UNKNOWN
Download-URL: https://pypi.org/project/garnett/
Keywords: simulation trajectory formats particle
Platform: UNKNOWN
Classifier: Intended Audience :: Science/Research
Classifier: License :: OSI Approved :: BSD License
Classifier: Topic :: Scientific/Engineering :: Physics
Requires-Python: >=3.5, <4
Requires-Dist: deprecation (>=2)
Requires-Dist: numpy (>=1.14)
Requires-Dist: rowan (>=1.2)
Requires-Dist: tqdm (>=4.35)
